yahoo_display_api/__init__.py
yahoo_display_api/api_client.py
yahoo_display_api/configuration.py
yahoo_display_api/exceptions.py
yahoo_display_api/rest.py
yahoo_display_api/api/__init__.py
yahoo_display_api/api/account_authority_service_api.py
yahoo_display_api/api/account_link_service_api.py
yahoo_display_api/api/account_management_service_api.py
yahoo_display_api/api/account_service_api.py
yahoo_display_api/api/account_tracking_url_service_api.py
yahoo_display_api/api/ad_group_ad_label_service_api.py
yahoo_display_api/api/ad_group_ad_service_api.py
yahoo_display_api/api/ad_group_label_service_api.py
yahoo_display_api/api/ad_group_service_api.py
yahoo_display_api/api/ad_group_target_service_api.py
yahoo_display_api/api/audit_log_service_api.py
yahoo_display_api/api/balance_service_api.py
yahoo_display_api/api/brand_lift_service_api.py
yahoo_display_api/api/budget_order_service_api.py
yahoo_display_api/api/campaign_label_service_api.py
yahoo_display_api/api/campaign_service_api.py
yahoo_display_api/api/contents_keyword_idea_service_api.py
yahoo_display_api/api/contents_keyword_list_service_api.py
yahoo_display_api/api/conversion_group_service_api.py
yahoo_display_api/api/conversion_tracker_service_api.py
yahoo_display_api/api/dictionary_service_api.py
yahoo_display_api/api/feed_data_service_api.py
yahoo_display_api/api/feed_ftp_request_service_api.py
yahoo_display_api/api/feed_ftp_service_api.py
yahoo_display_api/api/feed_item_service_api.py
yahoo_display_api/api/feed_service_api.py
yahoo_display_api/api/feed_set_service_api.py
yahoo_display_api/api/guaranteed_ad_group_ad_service_api.py
yahoo_display_api/api/guaranteed_ad_group_service_api.py
yahoo_display_api/api/guaranteed_campaign_service_api.py
yahoo_display_api/api/guaranteed_inventory_service_api.py
yahoo_display_api/api/guaranteed_preview_service_api.py
yahoo_display_api/api/guaranteed_reservation_service_api.py
yahoo_display_api/api/guaranteed_simulation_service_api.py
yahoo_display_api-1.0.0.dist-info/METADATA
yahoo_display_api-1.0.0.dist-info/WHEEL
yahoo_display_api-1.0.0.dist-info/top_level.txt
yahoo_display_api-1.0.0.dist-info/RECORD
